requests_package/__init__.py
requests_package/main.py
requests_package/test_main.py
requests_package-1.0.2.dist-info/LICENSE
requests_package-1.0.2.dist-info/METADATA
requests_package-1.0.2.dist-info/WHEEL
requests_package-1.0.2.dist-info/top_level.txt
requests_package-1.0.2.dist-info/RECORD
